{
    "1": {
        "id": 1,
        "formationId": "1",
        "formationLevel": "1",
        "skillId": "1",
        "ver": ""
    },
    "2": {
        "id": 2,
        "formationId": "1",
        "formationLevel": "1",
        "skillId": "2",
        "ver": ""
    },
    "3": {
        "id": 3,
        "formationId": "2",
        "formationLevel": "1",
        "skillId": "3",
        "ver": ""
    },
    "4": {
        "id": 4,
        "formationId": "3",
        "formationLevel": "1",
        "skillId": "4",
        "ver": ""
    }
}
