{
    "1": {
        "id": 1,
        "exp": 30,
        "ver": "1.0.0"
    },
    "2": {
        "id": 2,
        "exp": 36,
        "ver": "1.0.0"
    },
    "3": {
        "id": 3,
        "exp": 48,
        "ver": "1.0.0"
    },
    "4": {
        "id": 4,
        "exp": 72,
        "ver": "1.0.0"
    },
    "5": {
        "id": 5,
        "exp": 96,
        "ver": "1.0.0"
    },
    "6": {
        "id": 6,
        "exp": 120,
        "ver": "1.0.0"
    },
    "7": {
        "id": 7,
        "exp": 156,
        "ver": "1.0.0"
    },
    "8": {
        "id": 8,
        "exp": 180,
        "ver": "1.0.0"
    },
    "9": {
        "id": 9,
        "exp": 216,
        "ver": "1.0.0"
    },
    "10": {
        "id": 10,
        "exp": 216,
        "ver": "1.0.0"
    },
    "11": {
        "id": 11,
        "exp": 252,
        "ver": "1.0.0"
    },
    "12": {
        "id": 12,
        "exp": 264,
        "ver": "1.0.0"
    },
    "13": {
        "id": 13,
        "exp": 264,
        "ver": "1.0.0"
    },
    "14": {
        "id": 14,
        "exp": 276,
        "ver": "1.0.0"
    },
    "15": {
        "id": 15,
        "exp": 288,
        "ver": "1.0.0"
    },
    "16": {
        "id": 16,
        "exp": 324,
        "ver": "1.0.0"
    },
    "17": {
        "id": 17,
        "exp": 336,
        "ver": "1.0.0"
    },
    "18": {
        "id": 18,
        "exp": 348,
        "ver": "1.0.0"
    },
    "19": {
        "id": 19,
        "exp": 348,
        "ver": "1.0.0"
    },
    "20": {
        "id": 20,
        "exp": 630,
        "ver": "1.0.0"
    },
    "21": {
        "id": 21,
        "exp": 651,
        "ver": "1.0.0"
    },
    "22": {
        "id": 22,
        "exp": 672,
        "ver": "1.0.0"
    },
    "23": {
        "id": 23,
        "exp": 693,
        "ver": "1.0.0"
    },
    "24": {
        "id": 24,
        "exp": 714,
        "ver": "1.0.0"
    },
    "25": {
        "id": 25,
        "exp": 735,
        "ver": "1.0.0"
    },
    "26": {
        "id": 26,
        "exp": 756,
        "ver": "1.0.0"
    },
    "27": {
        "id": 27,
        "exp": 777,
        "ver": "1.0.0"
    },
    "28": {
        "id": 28,
        "exp": 798,
        "ver": "1.0.0"
    },
    "29": {
        "id": 29,
        "exp": 819,
        "ver": "1.0.0"
    },
    "30": {
        "id": 30,
        "exp": 840,
        "ver": "1.0.0"
    },
    "31": {
        "id": 31,
        "exp": 1113,
        "ver": "1.0.0"
    },
    "32": {
        "id": 32,
        "exp": 1428,
        "ver": "1.0.0"
    },
    "33": {
        "id": 33,
        "exp": 1743,
        "ver": "1.0.0"
    },
    "34": {
        "id": 34,
        "exp": 2058,
        "ver": "1.0.0"
    },
    "35": {
        "id": 35,
        "exp": 2310,
        "ver": "1.0.0"
    },
    "36": {
        "id": 36,
        "exp": 2940,
        "ver": "1.0.0"
    },
    "37": {
        "id": 37,
        "exp": 3570,
        "ver": "1.0.0"
    },
    "38": {
        "id": 38,
        "exp": 4200,
        "ver": "1.0.0"
    },
    "39": {
        "id": 39,
        "exp": 4830,
        "ver": "1.0.0"
    },
    "40": {
        "id": 40,
        "exp": 5460,
        "ver": "1.0.0"
    },
    "41": {
        "id": 41,
        "exp": 6300,
        "ver": "1.0.0"
    },
    "42": {
        "id": 42,
        "exp": 6930,
        "ver": "1.0.0"
    },
    "43": {
        "id": 43,
        "exp": 7770,
        "ver": "1.0.0"
    },
    "44": {
        "id": 44,
        "exp": 8610,
        "ver": "1.0.0"
    },
    "45": {
        "id": 45,
        "exp": 9450,
        "ver": "1.0.0"
    },
    "46": {
        "id": 46,
        "exp": 10500,
        "ver": "1.0.0"
    },
    "47": {
        "id": 47,
        "exp": 11340,
        "ver": "1.0.0"
    },
    "48": {
        "id": 48,
        "exp": 12390,
        "ver": "1.0.0"
    },
    "49": {
        "id": 49,
        "exp": 13440,
        "ver": "1.0.0"
    },
    "50": {
        "id": 50,
        "exp": 14700,
        "ver": "1.0.0"
    },
    "51": {
        "id": 51,
        "exp": 15750,
        "ver": "1.0.0"
    },
    "52": {
        "id": 52,
        "exp": 17010,
        "ver": "1.0.0"
    },
    "53": {
        "id": 53,
        "exp": 18270,
        "ver": "1.0.0"
    },
    "54": {
        "id": 54,
        "exp": 19530,
        "ver": "1.0.0"
    },
    "55": {
        "id": 55,
        "exp": 21000,
        "ver": "1.0.0"
    },
    "56": {
        "id": 56,
        "exp": 23100,
        "ver": "1.0.0"
    },
    "57": {
        "id": 57,
        "exp": 23100,
        "ver": "1.0.0"
    },
    "58": {
        "id": 58,
        "exp": 25200,
        "ver": "1.0.0"
    },
    "59": {
        "id": 59,
        "exp": 27300,
        "ver": "1.0.0"
    },
    "60": {
        "id": 60,
        "exp": 29400,
        "ver": "1.0.0"
    },
    "61": {
        "id": 61,
        "exp": 31500,
        "ver": "1.0.0"
    },
    "62": {
        "id": 62,
        "exp": 31500,
        "ver": "1.0.0"
    },
    "63": {
        "id": 63,
        "exp": 33600,
        "ver": "1.0.0"
    },
    "64": {
        "id": 64,
        "exp": 35700,
        "ver": "1.0.0"
    },
    "65": {
        "id": 65,
        "exp": 37800,
        "ver": "1.0.0"
    },
    "66": {
        "id": 66,
        "exp": 42000,
        "ver": "1.0.0"
    },
    "67": {
        "id": 67,
        "exp": 44100,
        "ver": "1.0.0"
    },
    "68": {
        "id": 68,
        "exp": 46200,
        "ver": "1.0.0"
    },
    "69": {
        "id": 69,
        "exp": 48300,
        "ver": "1.0.0"
    },
    "70": {
        "id": 70,
        "exp": 50400,
        "ver": "1.0.0"
    },
    "71": {
        "id": 71,
        "exp": 54600,
        "ver": "1.0.0"
    },
    "72": {
        "id": 72,
        "exp": 56700,
        "ver": "1.0.0"
    },
    "73": {
        "id": 73,
        "exp": 58800,
        "ver": "1.0.0"
    },
    "74": {
        "id": 74,
        "exp": 63000,
        "ver": "1.0.0"
    },
    "75": {
        "id": 75,
        "exp": 65100,
        "ver": "1.0.0"
    },
    "76": {
        "id": 76,
        "exp": 69300,
        "ver": "1.0.0"
    },
    "77": {
        "id": 77,
        "exp": 73500,
        "ver": "1.0.0"
    },
    "78": {
        "id": 78,
        "exp": 75600,
        "ver": "1.0.0"
    },
    "79": {
        "id": 79,
        "exp": 79800,
        "ver": "1.0.0"
    },
    "80": {
        "id": 80,
        "exp": 84000,
        "ver": "1.0.0"
    },
    "81": {
        "id": 81,
        "exp": 88200,
        "ver": "1.0.0"
    },
    "82": {
        "id": 82,
        "exp": 92400,
        "ver": "1.0.0"
    },
    "83": {
        "id": 83,
        "exp": 96600,
        "ver": "1.0.0"
    },
    "84": {
        "id": 84,
        "exp": 100800,
        "ver": "1.0.0"
    },
    "85": {
        "id": 85,
        "exp": 107100,
        "ver": "1.0.0"
    },
    "86": {
        "id": 86,
        "exp": 111300,
        "ver": "1.0.0"
    },
    "87": {
        "id": 87,
        "exp": 115500,
        "ver": "1.0.0"
    },
    "88": {
        "id": 88,
        "exp": 119700,
        "ver": "1.0.0"
    },
    "89": {
        "id": 89,
        "exp": 123900,
        "ver": "1.0.0"
    },
    "90": {
        "id": 90,
        "exp": 128100,
        "ver": "1.0.0"
    }
}
