{
    "1": {
        "id": 1,
        "AI": "ai_caocao",
        "asset": "1",
        "camp": 1,
        "gender": 1,
        "exclusiveItemId": 26,
        "noteStar": "S",
        "type": 3,
        "subType": 1,
        "damageType": 1,
        "maxLevel": 90,
        "initialStar": 1,
        "finalStar": 5,
        "initialQuality": 1,
        "finalQuality": 10,
        "qualityLevelType": 1,
        "baseStrength": 72,
        "baseIntelligence": 92,
        "baseLeadership": 99,
        "baseHP": 960,
        "baseMP": 32,
        "baseAtk": 80,
        "basePower": 0,
        "baseAr": 32,
        "baseRes": 16,
        "strengthGain": "2.62",
        "intelligenceGain": "3.5",
        "leadershipGain": "4.4",
        "formationId": 2,
        "soldierId": 4,
        "speed": 250,
        "strikeCD": "1",
        "ver": "1.0.0",
        "name_zhCN": "\u66f9\u64cd",
        "description_zhCN": "\u66f9\u64cd\u6682\u65e0\u63cf\u8ff0"
    },
    "2": {
        "id": 2,
        "AI": "ai_simayi",
        "asset": "2",
        "camp": 1,
        "gender": 1,
        "exclusiveItemId": 26,
        "noteStar": "S",
        "type": 2,
        "subType": 1,
        "damageType": 1,
        "maxLevel": 90,
        "initialStar": 1,
        "finalStar": 5,
        "initialQuality": 1,
        "finalQuality": 10,
        "qualityLevelType": 1,
        "baseStrength": 62,
        "baseIntelligence": 97,
        "baseLeadership": 91,
        "baseHP": 800,
        "baseMP": 100,
        "baseAtk": 50,
        "basePower": 200,
        "baseAr": 0,
        "baseRes": 60,
        "strengthGain": "2.4",
        "intelligenceGain": "4.7",
        "leadershipGain": "3.45",
        "formationId": 2,
        "soldierId": 5,
        "speed": 250,
        "strikeCD": "1.2",
        "ver": "1.0.0",
        "name_zhCN": "\u53f8\u9a6c\u61ff",
        "description_zhCN": "\u53f8\u9a6c\u61ff\u6682\u65e0\u63cf\u8ff0"
    },
    "3": {
        "id": 3,
        "AI": "ai_xuchu",
        "asset": "3",
        "camp": 1,
        "gender": 1,
        "exclusiveItemId": 26,
        "noteStar": "S",
        "type": 1,
        "subType": 1,
        "damageType": 1,
        "maxLevel": 90,
        "initialStar": 1,
        "finalStar": 5,
        "initialQuality": 1,
        "finalQuality": 10,
        "qualityLevelType": 1,
        "baseStrength": 98,
        "baseIntelligence": 42,
        "baseLeadership": 76,
        "baseHP": 1600,
        "baseMP": 48,
        "baseAtk": 160,
        "basePower": 0,
        "baseAr": 48,
        "baseRes": 0,
        "strengthGain": "5",
        "intelligenceGain": "1.5",
        "leadershipGain": "3.5",
        "formationId": 4,
        "soldierId": 3,
        "speed": 250,
        "strikeCD": "0.8",
        "ver": "1.0.0",
        "name_zhCN": "\u8bb8\u891a",
        "description_zhCN": "\u8bb8\u891a\u6682\u65e0\u63cf\u8ff0"
    },
    "4": {
        "id": 4,
        "AI": "ai_zhugeliang",
        "asset": "4",
        "camp": 2,
        "gender": 1,
        "exclusiveItemId": 27,
        "noteStar": "S",
        "type": 2,
        "subType": 1,
        "damageType": 1,
        "maxLevel": 90,
        "initialStar": 1,
        "finalStar": 5,
        "initialQuality": 1,
        "finalQuality": 10,
        "qualityLevelType": 1,
        "baseStrength": 33,
        "baseIntelligence": 100,
        "baseLeadership": 92,
        "baseHP": 800,
        "baseMP": 100,
        "baseAtk": 50,
        "basePower": 200,
        "baseAr": 0,
        "baseRes": 60,
        "strengthGain": "1.85",
        "intelligenceGain": "5.2",
        "leadershipGain": "3.5",
        "formationId": 3,
        "soldierId": 2,
        "speed": 250,
        "strikeCD": "1.2",
        "ver": "1.0.0",
        "name_zhCN": "\u8bf8\u845b\u4eae",
        "description_zhCN": "\u8bf8\u845b\u4eae\u6682\u65e0\u63cf\u8ff0"
    },
    "5": {
        "id": 5,
        "AI": "ai_guanyu",
        "asset": "5",
        "camp": 2,
        "gender": 1,
        "exclusiveItemId": 27,
        "noteStar": "S",
        "type": 1,
        "subType": 1,
        "damageType": 1,
        "maxLevel": 90,
        "initialStar": 1,
        "finalStar": 5,
        "initialQuality": 1,
        "finalQuality": 10,
        "qualityLevelType": 1,
        "baseStrength": 97,
        "baseIntelligence": 70,
        "baseLeadership": 83,
        "baseHP": 1600,
        "baseMP": 48,
        "baseAtk": 160,
        "basePower": 0,
        "baseAr": 48,
        "baseRes": 0,
        "strengthGain": "5",
        "intelligenceGain": "2.5",
        "leadershipGain": "3",
        "formationId": 5,
        "soldierId": 4,
        "speed": 250,
        "strikeCD": "0.8",
        "ver": "1.0.0",
        "name_zhCN": "\u5173\u7fbd",
        "description_zhCN": "\u5173\u7fbd\u6682\u65e0\u63cf\u8ff0"
    },
    "8": {
        "id": 8,
        "AI": "ai_zhangfei",
        "asset": "8",
        "camp": 2,
        "gender": 1,
        "exclusiveItemId": 27,
        "noteStar": "S",
        "type": 1,
        "subType": 1,
        "damageType": 1,
        "maxLevel": 90,
        "initialStar": 1,
        "finalStar": 5,
        "initialQuality": 1,
        "finalQuality": 10,
        "qualityLevelType": 1,
        "baseStrength": 98,
        "baseIntelligence": 55,
        "baseLeadership": 81,
        "baseHP": 1600,
        "baseMP": 48,
        "baseAtk": 160,
        "basePower": 0,
        "baseAr": 48,
        "baseRes": 0,
        "strengthGain": "5.3",
        "intelligenceGain": "1.2",
        "leadershipGain": "3.7",
        "formationId": 2,
        "soldierId": 3,
        "speed": 250,
        "strikeCD": "0.8",
        "ver": "1.0.0",
        "name_zhCN": "\u5f20\u98de",
        "description_zhCN": "\u5f20\u98de\u6682\u65e0\u63cf\u8ff0"
    },
    "11": {
        "id": 11,
        "AI": "ai_lvbu",
        "asset": "11",
        "camp": 4,
        "gender": 1,
        "exclusiveItemId": 29,
        "noteStar": "S",
        "type": 1,
        "subType": 1,
        "damageType": 1,
        "maxLevel": 90,
        "initialStar": 1,
        "finalStar": 5,
        "initialQuality": 1,
        "finalQuality": 10,
        "qualityLevelType": 1,
        "baseStrength": 100,
        "baseIntelligence": 49,
        "baseLeadership": 91,
        "baseHP": 1600,
        "baseMP": 48,
        "baseAtk": 160,
        "basePower": 0,
        "baseAr": 48,
        "baseRes": 0,
        "strengthGain": "5.5",
        "intelligenceGain": "1.65",
        "leadershipGain": "3.45",
        "formationId": 2,
        "soldierId": 3,
        "speed": 250,
        "strikeCD": "0.8",
        "ver": "1.0.0",
        "name_zhCN": "\u5415\u5e03",
        "description_zhCN": "\u5415\u5e03\u6682\u65e0\u63cf\u8ff0"
    },
    "19": {
        "id": 19,
        "AI": "ai_liubei",
        "asset": "19",
        "camp": 2,
        "gender": 1,
        "exclusiveItemId": 27,
        "noteStar": "A",
        "type": 3,
        "subType": 1,
        "damageType": 1,
        "maxLevel": 90,
        "initialStar": 1,
        "finalStar": 5,
        "initialQuality": 1,
        "finalQuality": 10,
        "qualityLevelType": 1,
        "baseStrength": 74,
        "baseIntelligence": 73,
        "baseLeadership": 75,
        "baseHP": 640,
        "baseMP": 16,
        "baseAtk": 64,
        "basePower": 0,
        "baseAr": 16,
        "baseRes": 16,
        "strengthGain": "2.75",
        "intelligenceGain": "2.65",
        "leadershipGain": "3.8",
        "formationId": 1,
        "soldierId": 1,
        "speed": 250,
        "strikeCD": "1",
        "ver": "1.0.0",
        "name_zhCN": "\u5218\u5907",
        "description_zhCN": "\u5218\u5907\u6682\u65e0\u63cf\u8ff0"
    },
    "21": {
        "id": 21,
        "AI": "ai_sunquan",
        "asset": "21",
        "camp": 3,
        "gender": 1,
        "exclusiveItemId": 28,
        "noteStar": "A",
        "type": 3,
        "subType": 1,
        "damageType": 1,
        "maxLevel": 90,
        "initialStar": 1,
        "finalStar": 5,
        "initialQuality": 1,
        "finalQuality": 10,
        "qualityLevelType": 1,
        "baseStrength": 67,
        "baseIntelligence": 83,
        "baseLeadership": 73,
        "baseHP": 640,
        "baseMP": 16,
        "baseAtk": 64,
        "basePower": 0,
        "baseAr": 16,
        "baseRes": 16,
        "strengthGain": "1.8",
        "intelligenceGain": "3.6",
        "leadershipGain": "3.5",
        "formationId": 1,
        "soldierId": 3,
        "speed": 250,
        "strikeCD": "1",
        "ver": "1.0.0",
        "name_zhCN": "\u5b59\u6743",
        "description_zhCN": "\u5b59\u6743\u6682\u65e0\u63cf\u8ff0"
    },
    "40": {
        "id": 40,
        "AI": "ai_daqiao",
        "asset": "40",
        "camp": 3,
        "gender": 2,
        "exclusiveItemId": 28,
        "noteStar": "B",
        "type": 2,
        "subType": 1,
        "damageType": 1,
        "maxLevel": 90,
        "initialStar": 1,
        "finalStar": 5,
        "initialQuality": 1,
        "finalQuality": 10,
        "qualityLevelType": 1,
        "baseStrength": 53,
        "baseIntelligence": 74,
        "baseLeadership": 72,
        "baseHP": 600,
        "baseMP": 40,
        "baseAtk": 20,
        "basePower": 120,
        "baseAr": 0,
        "baseRes": 20,
        "strengthGain": "1.85",
        "intelligenceGain": "3.9",
        "leadershipGain": "2.2",
        "formationId": 4,
        "soldierId": 4,
        "speed": 250,
        "strikeCD": "1.2",
        "ver": "1.0.0",
        "name_zhCN": "\u5927\u4e54",
        "description_zhCN": "\u5927\u4e54\u6682\u65e0\u63cf\u8ff0"
    }
}
